lolatents/__init__.py
lolatents/lol_numpy.py
lolatents/lol_torch.py
lolatents-0.1.1.dist-info/licenses/LICENSE
lolatents-0.1.1.dist-info/METADATA
lolatents-0.1.1.dist-info/WHEEL
lolatents-0.1.1.dist-info/top_level.txt
lolatents-0.1.1.dist-info/RECORD
