Metadata-Version: 2.4
Name: lolatents
Version: 0.1.1
Summary: Toolkit to form subspaces of latent spaces and more in diffusion models and other latent variable models.
Author-email: Erik Bodin <mail@erikbodin.com>
License-Expression: MIT
Classifier: Programming Language :: Python :: 3
Requires-Python: >=3.6
License-File: LICENSE
Requires-Dist: numpy>=2.0.0
Requires-Dist: beartype>=0.19.0
Requires-Dist: scipy>=1.10.0
Requires-Dist: jaxtyping>=0.2.38
Dynamic: license-file
